SitanfuCs231nJuanjiShenjingwangluoKechengBijiFanyi/README.md
SitanfuCs231nJuanjiShenjingwangluoKechengBijiFanyi/__init__.py
SitanfuCs231nJuanjiShenjingwangluoKechengBijiFanyi/__main__.py
SitanfuCs231nJuanjiShenjingwangluoKechengBijiFanyi/file.epub
SitanfuCs231nJuanjiShenjingwangluoKechengBijiFanyi/index.html
SitanfuCs231nJuanjiShenjingwangluoKechengBijiFanyi/css/__init__.py
SitanfuCs231nJuanjiShenjingwangluoKechengBijiFanyi/css/annotations.css
SitanfuCs231nJuanjiShenjingwangluoKechengBijiFanyi/css/main.css
SitanfuCs231nJuanjiShenjingwangluoKechengBijiFanyi/css/normalize.css
SitanfuCs231nJuanjiShenjingwangluoKechengBijiFanyi/css/popup.css
SitanfuCs231nJuanjiShenjingwangluoKechengBijiFanyi/font/__init__.py
SitanfuCs231nJuanjiShenjingwangluoKechengBijiFanyi/font/fontello.eot
SitanfuCs231nJuanjiShenjingwangluoKechengBijiFanyi/font/fontello.svg
SitanfuCs231nJuanjiShenjingwangluoKechengBijiFanyi/font/fontello.ttf
SitanfuCs231nJuanjiShenjingwangluoKechengBijiFanyi/font/fontello.woff
SitanfuCs231nJuanjiShenjingwangluoKechengBijiFanyi/img/__init__.py
SitanfuCs231nJuanjiShenjingwangluoKechengBijiFanyi/img/annotator-glyph-sprite.png
SitanfuCs231nJuanjiShenjingwangluoKechengBijiFanyi/img/annotator-icon-sprite.png
SitanfuCs231nJuanjiShenjingwangluoKechengBijiFanyi/img/apple-touch-icon.png
SitanfuCs231nJuanjiShenjingwangluoKechengBijiFanyi/img/cancelfullscreen.png
SitanfuCs231nJuanjiShenjingwangluoKechengBijiFanyi/img/close.png
SitanfuCs231nJuanjiShenjingwangluoKechengBijiFanyi/img/fullscreen.png
SitanfuCs231nJuanjiShenjingwangluoKechengBijiFanyi/img/loader.gif
SitanfuCs231nJuanjiShenjingwangluoKechengBijiFanyi/img/menu-icon.png
SitanfuCs231nJuanjiShenjingwangluoKechengBijiFanyi/img/save.png
SitanfuCs231nJuanjiShenjingwangluoKechengBijiFanyi/img/saved.png
SitanfuCs231nJuanjiShenjingwangluoKechengBijiFanyi/img/settings-s.png
SitanfuCs231nJuanjiShenjingwangluoKechengBijiFanyi/img/settings.png
SitanfuCs231nJuanjiShenjingwangluoKechengBijiFanyi/img/star.png
sitanfu_cs231n_juanji_shenjingwangluo_kecheng_biji_fanyi-2024.3.2.0.dist-info/METADATA
sitanfu_cs231n_juanji_shenjingwangluo_kecheng_biji_fanyi-2024.3.2.0.dist-info/WHEEL
sitanfu_cs231n_juanji_shenjingwangluo_kecheng_biji_fanyi-2024.3.2.0.dist-info/entry_points.txt
sitanfu_cs231n_juanji_shenjingwangluo_kecheng_biji_fanyi-2024.3.2.0.dist-info/top_level.txt
sitanfu_cs231n_juanji_shenjingwangluo_kecheng_biji_fanyi-2024.3.2.0.dist-info/RECORD
